LICENSE
MANIFEST.in
README.rst
setup.cfg
setup.py
versioneer.py
tpDcc/__init__.py
tpDcc/tools/__init__.py
tpDcc/tools/nameit/__init__.py
tpDcc/tools/nameit/__logging__.ini
tpDcc/tools/nameit/__version__.py
tpDcc/tools/nameit/_version.py
tpDcc/tools/nameit/core/__init__.py
tpDcc/tools/nameit/core/consts.py
tpDcc/tools/nameit/core/lib.py
tpDcc/tools/nameit/core/tool.py
tpDcc/tools/nameit/core/toolset.py
tpDcc/tools/nameit/data/naming_data.yml
tpDcc/tools/nameit/resources/icons/color/rename.png
tpDcc/tools/nameit/resources/icons/default/rename.png
tpDcc/tools/nameit/widgets/__init__.py
tpDcc/tools/nameit/widgets/nameit.py
tpDcc_tools_nameit.egg-info/PKG-INFO
tpDcc_tools_nameit.egg-info/SOURCES.txt
tpDcc_tools_nameit.egg-info/dependency_links.txt
tpDcc_tools_nameit.egg-info/not-zip-safe
tpDcc_tools_nameit.egg-info/requires.txt
tpDcc_tools_nameit.egg-info/top_level.txt