Metadata-Version: 2.1
Name: tpDcc-tools-nameit
Version: 0.0.9
Summary: Tool that manages nomenclature in a DCC agnostic way.
Home-page: https://github.com/tpDcc/tpDcc-tools-nameit
Author: Tomas Poveda
Author-email: tpovedatd@gmail.com
License: MIT
Platform: UNKNOWN
Provides-Extra: dev
Provides-Extra: test
